[{"name":"sql.active_record","payload":{"sql":"SELECT \"mid_points\".* FROM \"mid_points\"","name":"MidPoint Load","connection_id":51150660,"statement_name":null,"binds":[],"line":87,"filename":"/home/avid/2-biketripplanner_project2/bike_trip_planner/app/models/bike_route.rb","method":"get_points_in_range"},"time":"2015-03-24T20:23:43.711+11:00","transaction_id":"5d7862f9f6d8526dd32b","end":"2015-03-24T20:23:43.713+11:00","children":[],"duration":1.7879580000000002},{"name":"meta_request.log","payload":{"message":"starting loop iteration","level":"info","line":21,"filename":"/home/avid/2-biketripplanner_project2/bike_trip_planner/app/models/bike_route.rb","method":"calc_bike_route"},"time":0,"transaction_id":0,"end":0,"children":[],"duration":0.0},{"name":"meta_request.log","payload":{"message":"finding closest entry point","level":"info","line":28,"filename":"/home/avid/2-biketripplanner_project2/bike_trip_planner/app/models/bike_route.rb","method":"calc_bike_route"},"time":0,"transaction_id":0,"end":0,"children":[],"duration":0.0},{"name":"meta_request.log","payload":{"message":"got closest entry point","level":"info","line":31,"filename":"/home/avid/2-biketripplanner_project2/bike_trip_planner/app/models/bike_route.rb","method":"calc_bike_route"},"time":0,"transaction_id":0,"end":0,"children":[],"duration":0.0},{"name":"meta_request.log","payload":{"message":[[0.0,0.0],[0.0,0.0]],"level":"info","line":38,"filename":"/home/avid/2-biketripplanner_project2/bike_trip_planner/app/models/bike_route.rb","method":"calc_bike_route"},"time":0,"transaction_id":0,"end":0,"children":[],"duration":0.0},{"name":"render_template.action_view","payload":{"identifier":"/home/avid/2-biketripplanner_project2/bike_trip_planner/app/views/bike_routes/index.html.erb","layout":"layouts/application"},"time":"2015-03-24T20:23:43.721+11:00","transaction_id":"85a99d34fac51b97826b","end":"2015-03-24T20:23:43.721+11:00","children":[],"duration":0.057862000000000004},{"name":"process_action.action_controller","payload":{"controller":"BikeRoutesController","action":"index","params":{"controller":"bike_routes","action":"index"},"format":"html","method":"GET","path":"/","status":200,"view_runtime":45.090683999999996,"db_runtime":1.428702},"time":"2015-03-24T20:23:43.711+11:00","transaction_id":"85a99d34fac51b97826b","end":"2015-03-24T20:23:43.765+11:00","children":[],"duration":54.321363}]